spryx_agents/__init__.py
spryx_agents/client.py
spryx_agents/resources/__init__.py
spryx_agents/resources/agents.py
spryx_agents/resources/chats.py
spryx_agents/resources/credential_types.py
spryx_agents/resources/credentials.py
spryx_agents/resources/embedding_usages.py
spryx_agents/resources/files.py
spryx_agents/resources/integrations.py
spryx_agents/resources/org_config.py
spryx_agents/resources/vector_stores.py
spryx_agents/types/__init__.py
spryx_agents/types/agent.py
spryx_agents/types/vector_store.py
spryx_agents-0.1.13.dist-info/LICENSE
spryx_agents-0.1.13.dist-info/METADATA
spryx_agents-0.1.13.dist-info/WHEEL
spryx_agents-0.1.13.dist-info/RECORD
