Metadata-Version: 2.3
Name: spryx-agents
Version: 0.1.13
Summary: 
Author: Pedro Cantidio
Author-email: pedro@spryx.ai
Requires-Python: >=3.11
Classifier: Programming Language :: Python :: 3
Classifier: Programming Language :: Python :: 3.11
Classifier: Programming Language :: Python :: 3.12
Classifier: Programming Language :: Python :: 3.13
Requires-Dist: spryx-http (>=0.1.7,<0.2.0)
